{
    "form": [
        {
            "name": "Textbox",
            "path": "/textbox"
        },
        {
            "name": "TextboxGroup",
            "path": "/textboxgroup"
        },
        {
            "name": "Textarea",
            "path": "/textarea"
        },
        {
            "name": "Textlabel",
            "path": "/textlabel"
        },
        {
            "name": "Checkbox",
            "path": "/checkbox"
        },
        {
            "name": "Dropdown",
            "path": "/dropdown"
        },
        {
            "name": "Datepicker",
            "path": "/datepicker"
        },
        {
            "name": "Radio Group",
            "path": "/radiogroup"
        },
        {
            "name": "Radio Button",
            "path": "/radiobtn"
        },
        {
            "name": "Rating",
            "path": "/rating"
        },
        {
            "name": "Toggle",
            "path": "/toggle"
        },
        {
            "name": "Slider",
            "path": "/slider"
        },
        {
            "name": "Stepper",
            "path": "/stepper"
        },
        {
            "name": "Timepicker",
            "path": "/timepicker"
        },
        {
            "name": "Image Cropper",
            "path": "/imagecropper"
        }
    ],
    "ui": [
        {
            "name": "Button",
            "path": "/button"
        },
        {
            "name": "Tooltip",
            "path": "/tooltip"
        },
        {
            "name": "Loader",
            "path": "/loader"
        },
        {
            "name": "Progress Bar",
            "path": "/progressbar"
        },
        {
            "name": "Carousel",
            "path": "/carousel"
        },
        {
            "name": "Pagination/DotNav",
            "path": "/pagination"
        },
        {
            "name": "Timeline",
            "path": "/timeline"
        },
        {
            "name": "Step Tracker",
            "path": "/steptracker"
        },
        {
            "name": "Breadcrumb",
            "path": "/breadcrumb"
        },
        {
            "name": "Accordion",
            "path": "/accordion"
        },
        {
            "name": "Tabs",
            "path": "/tabs"
        },
        {
            "name": "Notification",
            "path": "/notification"
        }
    ],
    "other": [
        {
            "name": "Dialogue",
            "path": "/dialogue"
        },
        {
            "name": "Charts",
            "path": "/chart"
        },
        {
            "name": "Image Holder",
            "path": "/image"
        },
        {
            "name": "Inline Link",
            "path": "/inlinelink"
        },
        {
            "name": "Video Holder",
            "path": "/video"
        },
        {
            "name": "Timer",
            "path": "/timer"
        },
        {
            "name": "Icons",
            "path": "/icons"
        }
    ]
}